{"_id":"60d7fdbb17475a2460a7bebd","title":" Plugins jQuery ideales para desarrolladores principiantes","author":"Alejandro","imageGuid":"uploads/1345a460-d6e8-11eb-a3b5-b58a81333111.png","p1":"Los plugins jQuery tienen diversos propósitos. Algunos te permiten crear elementos básicos y tienen una única función, mientras que otros pueden tener diversas configuraciones y opciones. Pero no cabe duda que todos ellos son recursos de gran utilidad en cualquier proyecto de desarrollo web. Gracias a los plugins jQuery, los desarrolladores pueden añadir funciones y elementos a sus sitios web de forma rápida y sencilla, de esta manera ahorran tiempo que pueden emplear para realizar pruebas con mayor detenimiento o para cualquier otra tarea esencial en el proyecto."}